vqapi/README.md
vqapi/__init__.py
vqapi/blockable_module.py
vqapi/bqclass.py
vqapi/casauth.py
vqapi/cmd.py
vqapi/comm.py
vqapi/exception.py
vqapi/loggingpool.py
vqapi/plugins.py
vqapi/util.py
vqapi/version.py
vqapi/vqclass.py
vqapi/vqquery.py
vqapi/RequestsMonkeyPatch/__init__.py
vqapi/RequestsMonkeyPatch/monkeypatch.py
vqapi/RequestsMonkeyPatch/requests_patch.py
vqapi/services/__init__.py
vqapi/services/base_proxy.py
vqapi/services/core_services.py
vqapi/services/factory.py
vqapi/services/image_proxy.py
vqapi/services/import_proxy.py
vqapi/services/table_proxy.py
vqapi/services/threadpool.py
viqi_api-0.6.22.dist-info/METADATA
viqi_api-0.6.22.dist-info/WHEEL
viqi_api-0.6.22.dist-info/top_level.txt
viqi_api-0.6.22.dist-info/RECORD
