Metadata-Version: 2.4
Name: viqi_api
Version: 0.6.22
Summary: ViQi Python API
Author-email: ViQi Inc <info@viqi.org>
Project-URL: homepage, https://www.viqi.org
Classifier: Programming Language :: Python :: 3
Classifier: Programming Language :: Python :: 3.8
Classifier: Programming Language :: Python :: 3.10
Requires-Python: >=3.8
Requires-Dist: configparser
Requires-Dist: bisque-metadoc>=0.6.4.16
Requires-Dist: tifffile
Requires-Dist: furl
Requires-Dist: simplejson
Requires-Dist: shortuuid>=1.0.8
Requires-Dist: tenacity
Requires-Dist: importlib-metadata; python_version < "3.10"
Requires-Dist: boto3>=1.28.52
Requires-Dist: urllib3>=2.0.0
Requires-Dist: requests>=2.32.0
Requires-Dist: requests-cache>=1.1.0
Requires-Dist: requests-toolbelt>=1.0.0
Provides-Extra: test
Requires-Dist: pytest; extra == "test"
Requires-Dist: pytest-cov; extra == "test"
Requires-Dist: webtest; extra == "test"
Provides-Extra: image-service
Requires-Dist: tifffile; extra == "image-service"
Requires-Dist: tables; extra == "image-service"
Provides-Extra: table-service
Requires-Dist: numpy; extra == "table-service"
Requires-Dist: pandas; extra == "table-service"
Requires-Dist: tables; extra == "table-service"
